datasus_dbc-0.1.3.dist-info/METADATA
datasus_dbc-0.1.3.dist-info/WHEEL
datasus_dbc/__init__.py
datasus_dbc/__init__.pyi
datasus_dbc/py.typed
datasus_dbc/datasus_dbc.cpython-311-aarch64-linux-gnu.so
datasus_dbc-0.1.3.dist-info/RECORD
