Metadata-Version: 2.3
Name: datasus-dbc
Version: 0.1.3
Classifier: Programming Language :: Rust
Classifier: License :: OSI Approved :: MIT License
Classifier: Operating System :: OS Independent
Classifier: Topic :: System :: Archiving :: Compression
Summary: Decompress DATASUS's dbc files into dbf files
Keywords: dbc,dbf,datasus,compression,blast
Author: Murilo Matsubara <murilo.matsubara@gmail.com>
Author-email: Murilo Matsubara <murilo.matsubara@gmail.com>
License: MIT
Requires-Python: >=3.8
Project-URL: Source, https://github.com/mymatsubara/datasus-dbc-py
